_mutable_lattice.cp310-win32.pyd
mutable_lattice/__init__.py
mutable_lattice/bench.py
mutable_lattice/pylattice.py
mutable_lattice/test.py
mutable_lattice-0.1.1.dist-info/licenses/LICENSE
mutable_lattice-0.1.1.dist-info/METADATA
mutable_lattice-0.1.1.dist-info/WHEEL
mutable_lattice-0.1.1.dist-info/top_level.txt
mutable_lattice-0.1.1.dist-info/RECORD
