Metadata-Version: 2.4
Name: mutable_lattice
Version: 0.1.1
Summary: integer linear algebra using mutable sublattices of Z^n
Author-email: Dennis Sweeney <sweeney.427@osu.edu>
License-Expression: GPL-3.0-or-later
Project-URL: Homepage, https://github.com/sweeneyde/mutable_lattice
Project-URL: Bug Tracker, https://github.com/sweeneyde/mutable_lattice
Classifier: Programming Language :: Python :: 3
Classifier: Topic :: Scientific/Engineering :: Mathematics
Classifier: Operating System :: OS Independent
Requires-Python: >=3.10
License-File: LICENSE
Dynamic: license-file
